collimator/__init__.py
collimator/version.py
collimator_ai-0.0.1a0.dist-info/METADATA
collimator_ai-0.0.1a0.dist-info/WHEEL
collimator_ai-0.0.1a0.dist-info/top_level.txt
collimator_ai-0.0.1a0.dist-info/RECORD
